{"IdPlayer":"200940821","Name":[{"Locale":"en-GB","Description":"Diego Fagundez"}],"Alias":[{"Locale":"en-GB","Description":"Diego Fagundez"}],"BirthDate":"1995-02-14T00:00:00Z","Weight":68.0,"Height":173.0,"BirthPlace":"URU","IdCountry":"URU","InternationalCaps":0,"InternationalDebut":null,"TopCompetitionDebut":null,"PictureUrl":null,"ThumbnailUrl":null,"TwitterAccount":null,"PreferredFoot":null,"MediaContent":[],"LocalizedTwitterAccounts":null,"Goals":0,"Properties":{"IdCBS":"200940821","IdInfostrada":"940821"},"IsUpdateable":null}