{"IdPlayer":"201281656","Name":[{"Locale":"en-GB","Description":"Scott Wright"}],"Alias":[{"Locale":"en-GB","Description":"Scott Wright"}],"BirthDate":"1997-08-08T00:00:00Z","Weight":65.0,"Height":175.0,"BirthPlace":"SCO","IdCountry":"SCO","InternationalCaps":0,"InternationalDebut":null,"TopCompetitionDebut":null,"PictureUrl":null,"ThumbnailUrl":null,"TwitterAccount":null,"PreferredFoot":null,"MediaContent":[],"LocalizedTwitterAccounts":null,"Goals":0,"Properties":{"IdCBS":"201281656","IdInfostrada":"1281656"},"IsUpdateable":null}