{"IdPlayer":"201311620","Name":[{"Locale":"en-GB","Description":"Franco ESCOBAR"}],"Alias":[{"Locale":"en-GB","Description":"Franco Escobar"}],"BirthDate":"1995-02-21T00:00:00Z","Weight":72.0,"Height":175.0,"BirthPlace":null,"IdCountry":"ARG","InternationalCaps":0,"InternationalDebut":null,"TopCompetitionDebut":null,"PictureUrl":null,"ThumbnailUrl":null,"TwitterAccount":null,"PreferredFoot":null,"MediaContent":[],"LocalizedTwitterAccounts":null,"Goals":0,"Properties":{"IdCBS":"201311620","IdInfostrada":"1311620"},"IsUpdateable":null}