{"IdPlayer":"201784871","Name":[{"Locale":"en-GB","Description":"Diego CAMPOS"}],"Alias":[{"Locale":"en-GB","Description":"Diego Campos"}],"BirthDate":"1995-10-01T00:00:00Z","Weight":0.0,"Height":0.0,"BirthPlace":null,"IdCountry":"CRC","InternationalCaps":0,"InternationalDebut":null,"TopCompetitionDebut":null,"PictureUrl":null,"ThumbnailUrl":null,"TwitterAccount":null,"PreferredFoot":null,"MediaContent":[],"LocalizedTwitterAccounts":null,"Goals":0,"Properties":{"IdCBS":"201784871","IdInfostrada":"1784871"},"IsUpdateable":null}