{"IdStage":"2000161109","IdMatch":"300384416","IdCompetition":"2000000103","IdSeason":"2000010811","IdGroup":null,"Event":[{"EventId":"20055601","IdTeam":null,"IdPlayer":null,"IdSubPlayer":null,"IdSubTeam":null,"Timestamp":null,"MatchMinute":null,"Period":1,"HomeGoals":0,"AwayGoals":0,"Type":9999,"TypeLocalized":[],"PositionX":null,"PositionY":null,"GoalGatePositionX":null,"GoalGatePositionY":null,"GoalGatePositionZ":null,"VarDetail":null,"HomePenaltyGoals":0,"AwayPenaltyGoals":0},{"EventId":"20055607","IdTeam":null,"IdPlayer":null,"IdSubPlayer":null,"IdSubTeam":null,"Timestamp":"2017-03-19T23:20:41.23Z","MatchMinute":"0'","Period":3,"HomeGoals":0,"AwayGoals":0,"Type":7,"TypeLocalized":[],"PositionX":null,"PositionY":null,"GoalGatePositionX":null,"GoalGatePositionY":null,"GoalGatePositionZ":null,"VarDetail":null,"HomePenaltyGoals":0,"AwayPenaltyGoals":0},{"EventId":"20055690","IdTeam":"2147482235","IdPlayer":"201040992","IdSubPlayer":null,"IdSubTeam":null,"Timestamp":"2017-03-19T23:45:41.23Z","MatchMinute":"25'","Period":3,"HomeGoals":0,"AwayGoals":0,"Type":2,"TypeLocalized":[],"PositionX":null,"PositionY":null,"GoalGatePositionX":null,"GoalGatePositionY":null,"GoalGatePositionZ":null,"VarDetail":null,"HomePenaltyGoals":0,"AwayPenaltyGoals":0},{"EventId":"20055693","IdTeam":"2147482235","IdPlayer":"200659287","IdSubPlayer":null,"IdSubTeam":null,"Timestamp":"2017-03-19T23:47:41.23Z","MatchMinute":"27'","Period":3,"HomeGoals":0,"AwayGoals":0,"Type":2,"TypeLocalized":[],"PositionX":null,"PositionY":null,"GoalGatePositionX":null,"GoalGatePositionY":null,"GoalGatePositionZ":null,"VarDetail":null,"HomePenaltyGoals":0,"AwayPenaltyGoals":0},{"EventId":"20055692","IdTeam":"2000000975","IdPlayer":"207851","IdSubPlayer":null,"IdSubTeam":null,"Timestamp":"2017-03-19T23:48:41.23Z","MatchMinute":"28'","Period":3,"HomeGoals":1,"AwayGoals":0,"Type":41,"TypeLocalized":[],"PositionX":null,"PositionY":null,"GoalGatePositionX":null,"GoalGatePositionY":null,"GoalGatePositionZ":null,"VarDetail":null,"HomePenaltyGoals":0,"AwayPenaltyGoals":0},{"EventId":"20055715","IdTeam":"2147482235","IdPlayer":"200778932","IdSubPlayer":null,"IdSubTeam":null,"Timestamp":"2017-03-19T23:50:41.23Z","MatchMinute":"30'","Period":3,"HomeGoals":1,"AwayGoals":0,"Type":2,"TypeLocalized":[],"PositionX":null,"PositionY":null,"GoalGatePositionX":null,"GoalGatePositionY":null,"GoalGatePositionZ":null,"VarDetail":null,"HomePenaltyGoals":0,"AwayPenaltyGoals":0},{"EventId":"20055735","IdTeam":null,"IdPlayer":null,"IdSubPlayer":null,"IdSubTeam":null,"Timestamp":"2017-03-20T00:07:02.23Z","MatchMinute":"45'+2'","Period":3,"HomeGoals":1,"AwayGoals":0,"Type":8,"TypeLocalized":[],"PositionX":null,"PositionY":null,"GoalGatePositionX":null,"GoalGatePositionY":null,"GoalGatePositionZ":null,"VarDetail":null,"HomePenaltyGoals":0,"AwayPenaltyGoals":0},{"EventId":"20055805","IdTeam":null,"IdPlayer":null,"IdSubPlayer":null,"IdSubTeam":null,"Timestamp":"2017-03-20T00:23:23.74Z","MatchMinute":"45'","Period":5,"HomeGoals":1,"AwayGoals":0,"Type":7,"TypeLocalized":[],"PositionX":null,"PositionY":null,"GoalGatePositionX":null,"GoalGatePositionY":null,"GoalGatePositionZ":null,"VarDetail":null,"HomePenaltyGoals":0,"AwayPenaltyGoals":0},{"EventId":"20055851","IdTeam":"2147482235","IdPlayer":"295914","IdSubPlayer":"267927","IdSubTeam":null,"Timestamp":"2017-03-20T00:35:23.74Z","MatchMinute":"57'","Period":5,"HomeGoals":1,"AwayGoals":1,"Type":0,"TypeLocalized":[],"PositionX":null,"PositionY":null,"GoalGatePositionX":null,"GoalGatePositionY":null,"GoalGatePositionZ":null,"VarDetail":null,"HomePenaltyGoals":0,"AwayPenaltyGoals":0},{"EventId":"20055573","IdTeam":"2147482235","IdPlayer":"200774791","IdSubPlayer":"200778932","IdSubTeam":null,"Timestamp":"2017-03-20T00:35:23.74Z","MatchMinute":"57'","Period":5,"HomeGoals":0,"AwayGoals":0,"Type":5,"TypeLocalized":[],"PositionX":null,"PositionY":null,"GoalGatePositionX":null,"GoalGatePositionY":null,"GoalGatePositionZ":null,"VarDetail":null,"HomePenaltyGoals":0,"AwayPenaltyGoals":0},{"EventId":"20055852","IdTeam":"2147482235","IdPlayer":"295914","IdSubPlayer":null,"IdSubTeam":null,"Timestamp":"2017-03-20T00:40:23.74Z","MatchMinute":"62'","Period":5,"HomeGoals":1,"AwayGoals":1,"Type":2,"TypeLocalized":[],"PositionX":null,"PositionY":null,"GoalGatePositionX":null,"GoalGatePositionY":null,"GoalGatePositionZ":null,"VarDetail":null,"HomePenaltyGoals":0,"AwayPenaltyGoals":0},{"EventId":"20055563","IdTeam":"2000000975","IdPlayer":"306142","IdSubPlayer":"201366478","IdSubTeam":null,"Timestamp":"2017-03-20T00:43:23.74Z","MatchMinute":"65'","Period":5,"HomeGoals":0,"AwayGoals":0,"Type":5,"TypeLocalized":[],"PositionX":null,"PositionY":null,"GoalGatePositionX":null,"GoalGatePositionY":null,"GoalGatePositionZ":null,"VarDetail":null,"HomePenaltyGoals":0,"AwayPenaltyGoals":0},{"EventId":"20055864","IdTeam":"2000000975","IdPlayer":"368991","IdSubPlayer":"305378","IdSubTeam":null,"Timestamp":"2017-03-20T00:44:23.74Z","MatchMinute":"66'","Period":5,"HomeGoals":2,"AwayGoals":1,"Type":0,"TypeLocalized":[],"PositionX":null,"PositionY":null,"GoalGatePositionX":null,"GoalGatePositionY":null,"GoalGatePositionZ":null,"VarDetail":null,"HomePenaltyGoals":0,"AwayPenaltyGoals":0},{"EventId":"20055572","IdTeam":"2147482235","IdPlayer":"201507329","IdSubPlayer":"201346408","IdSubTeam":null,"Timestamp":"2017-03-20T00:52:23.74Z","MatchMinute":"74'","Period":5,"HomeGoals":0,"AwayGoals":0,"Type":5,"TypeLocalized":[],"PositionX":null,"PositionY":null,"GoalGatePositionX":null,"GoalGatePositionY":null,"GoalGatePositionZ":null,"VarDetail":null,"HomePenaltyGoals":0,"AwayPenaltyGoals":0},{"EventId":"20055871","IdTeam":"2000000975","IdPlayer":"207851","IdSubPlayer":null,"IdSubTeam":null,"Timestamp":"2017-03-20T00:56:23.74Z","MatchMinute":"78'","Period":5,"HomeGoals":2,"AwayGoals":1,"Type":2,"TypeLocalized":[],"PositionX":null,"PositionY":null,"GoalGatePositionX":null,"GoalGatePositionY":null,"GoalGatePositionZ":null,"VarDetail":null,"HomePenaltyGoals":0,"AwayPenaltyGoals":0},{"EventId":"20055873","IdTeam":"2000000975","IdPlayer":"201245736","IdSubPlayer":"351670","IdSubTeam":null,"Timestamp":"2017-03-20T00:57:23.74Z","MatchMinute":"79'","Period":5,"HomeGoals":3,"AwayGoals":1,"Type":0,"TypeLocalized":[],"PositionX":null,"PositionY":null,"GoalGatePositionX":null,"GoalGatePositionY":null,"GoalGatePositionZ":null,"VarDetail":null,"HomePenaltyGoals":0,"AwayPenaltyGoals":0},{"EventId":"20055565","IdTeam":"2000000975","IdPlayer":"200924700","IdSubPlayer":"368991","IdSubTeam":null,"Timestamp":"2017-03-20T00:59:23.74Z","MatchMinute":"81'","Period":5,"HomeGoals":0,"AwayGoals":0,"Type":5,"TypeLocalized":[],"PositionX":null,"PositionY":null,"GoalGatePositionX":null,"GoalGatePositionY":null,"GoalGatePositionZ":null,"VarDetail":null,"HomePenaltyGoals":0,"AwayPenaltyGoals":0},{"EventId":"20055574","IdTeam":"2147482235","IdPlayer":"201480209","IdSubPlayer":"358251","IdSubTeam":null,"Timestamp":"2017-03-20T00:59:23.74Z","MatchMinute":"81'","Period":5,"HomeGoals":0,"AwayGoals":0,"Type":5,"TypeLocalized":[],"PositionX":null,"PositionY":null,"GoalGatePositionX":null,"GoalGatePositionY":null,"GoalGatePositionZ":null,"VarDetail":null,"HomePenaltyGoals":0,"AwayPenaltyGoals":0},{"EventId":"20055567","IdTeam":"2000000975","IdPlayer":"201614471","IdSubPlayer":"207851","IdSubTeam":null,"Timestamp":"2017-03-20T01:09:23.74Z","MatchMinute":"90'+1'","Period":5,"HomeGoals":0,"AwayGoals":0,"Type":5,"TypeLocalized":[],"PositionX":null,"PositionY":null,"GoalGatePositionX":null,"GoalGatePositionY":null,"GoalGatePositionZ":null,"VarDetail":null,"HomePenaltyGoals":0,"AwayPenaltyGoals":0},{"EventId":"20055880","IdTeam":"2000000975","IdPlayer":"306142","IdSubPlayer":null,"IdSubTeam":null,"Timestamp":"2017-03-20T01:10:23.74Z","MatchMinute":"90'+2'","Period":5,"HomeGoals":3,"AwayGoals":1,"Type":2,"TypeLocalized":[],"PositionX":null,"PositionY":null,"GoalGatePositionX":null,"GoalGatePositionY":null,"GoalGatePositionZ":null,"VarDetail":null,"HomePenaltyGoals":0,"AwayPenaltyGoals":0},{"EventId":"20055881","IdTeam":null,"IdPlayer":null,"IdSubPlayer":null,"IdSubTeam":null,"Timestamp":"2017-03-20T01:12:58.74Z","MatchMinute":"90'+5'","Period":5,"HomeGoals":3,"AwayGoals":1,"Type":8,"TypeLocalized":[],"PositionX":null,"PositionY":null,"GoalGatePositionX":null,"GoalGatePositionY":null,"GoalGatePositionZ":null,"VarDetail":null,"HomePenaltyGoals":0,"AwayPenaltyGoals":0},{"EventId":"-9223372036854775808","IdTeam":null,"IdPlayer":null,"IdSubPlayer":null,"IdSubTeam":null,"Timestamp":"2017-03-20T01:12:58.74Z","MatchMinute":"90'+5'","Period":5,"HomeGoals":3,"AwayGoals":1,"Type":26,"TypeLocalized":[],"PositionX":null,"PositionY":null,"GoalGatePositionX":null,"GoalGatePositionY":null,"GoalGatePositionZ":null,"VarDetail":null,"HomePenaltyGoals":0,"AwayPenaltyGoals":0}],"Properties":{"IdCBS":"300384416","IdInfostrada":"2155100"},"IsUpdateable":null}